{
  "options": {
    "by_ticker": {
      "USO": {
        "label": "United States Oil Fund ETF",
        "pc_ratio_volume": 0.895,
        "pc_ratio_oi": 1.031,
        "total_call_volume": 46781,
        "total_put_volume": 41865,
        "total_call_oi": 248751,
        "total_put_oi": 256561,
        "expiries_analyzed": 4
      },
      "XLE": {
        "label": "Energy Select Sector SPDR",
        "pc_ratio_volume": 1.214,
        "pc_ratio_oi": 0.922,
        "total_call_volume": 17324,
        "total_put_volume": 21029,
        "total_call_oi": 320420,
        "total_put_oi": 295443,
        "expiries_analyzed": 4
      }
    },
    "by_expiry": [
      {
        "ticker": "USO",
        "expiry": "2026-05-08",
        "pc_ratio_volume": 0.924,
        "pc_ratio_oi": 0.73,
        "total_call_volume": 20228,
        "total_put_volume": 18688,
        "total_call_oi": 79000,
        "total_put_oi": 57689,
        "max_call_oi_strike": 200.0,
        "max_put_oi_strike": 130.0,
        "avg_iv_calls": 1.3178,
        "avg_iv_puts": 2.3589,
        "iv_skew": 1.0411
      },
      {
        "ticker": "USO",
        "expiry": "2026-05-13",
        "pc_ratio_volume": 0.235,
        "pc_ratio_oi": 0.779,
        "total_call_volume": 10584,
        "total_put_volume": 2491,
        "total_call_oi": 11322,
        "total_put_oi": 8820,
        "max_call_oi_strike": 160.0,
        "max_put_oi_strike": 125.0,
        "avg_iv_calls": 0.8014,
        "avg_iv_puts": 0.9905,
        "iv_skew": 0.1891
      },
      {
        "ticker": "USO",
        "expiry": "2026-05-15",
        "pc_ratio_volume": 1.318,
        "pc_ratio_oi": 1.199,
        "total_call_volume": 15327,
        "total_put_volume": 20195,
        "total_call_oi": 157247,
        "total_put_oi": 188504,
        "max_call_oi_strike": 148.0,
        "max_put_oi_strike": 100.0,
        "avg_iv_calls": 0.6359,
        "avg_iv_puts": 1.1839,
        "iv_skew": 0.548
      },
      {
        "ticker": "USO",
        "expiry": "2026-05-20",
        "pc_ratio_volume": 0.765,
        "pc_ratio_oi": 1.31,
        "total_call_volume": 642,
        "total_put_volume": 491,
        "total_call_oi": 1182,
        "total_put_oi": 1548,
        "max_call_oi_strike": 140.0,
        "max_put_oi_strike": 130.0,
        "avg_iv_calls": 0.6488,
        "avg_iv_puts": 0.8476,
        "iv_skew": 0.1989
      },
      {
        "ticker": "XLE",
        "expiry": "2026-05-08",
        "pc_ratio_volume": 1.277,
        "pc_ratio_oi": 0.866,
        "total_call_volume": 3718,
        "total_put_volume": 4748,
        "total_call_oi": 46643,
        "total_put_oi": 40401,
        "max_call_oi_strike": 60.0,
        "max_put_oi_strike": 56.0,
        "avg_iv_calls": 0.9648,
        "avg_iv_puts": 0.9223,
        "iv_skew": -0.0424
      },
      {
        "ticker": "XLE",
        "expiry": "2026-05-15",
        "pc_ratio_volume": 0.99,
        "pc_ratio_oi": 0.902,
        "total_call_volume": 11494,
        "total_put_volume": 11378,
        "total_call_oi": 253898,
        "total_put_oi": 228991,
        "max_call_oi_strike": 60.0,
        "max_put_oi_strike": 55.0,
        "avg_iv_calls": 0.4478,
        "avg_iv_puts": 0.5417,
        "iv_skew": 0.094
      },
      {
        "ticker": "XLE",
        "expiry": "2026-05-22",
        "pc_ratio_volume": 1.36,
        "pc_ratio_oi": 1.541,
        "total_call_volume": 976,
        "total_put_volume": 1327,
        "total_call_oi": 10011,
        "total_put_oi": 15428,
        "max_call_oi_strike": 59.0,
        "max_put_oi_strike": 53.0,
        "avg_iv_calls": 0.4259,
        "avg_iv_puts": 0.4778,
        "iv_skew": 0.0519
      },
      {
        "ticker": "XLE",
        "expiry": "2026-05-29",
        "pc_ratio_volume": 3.148,
        "pc_ratio_oi": 1.077,
        "total_call_volume": 1136,
        "total_put_volume": 3576,
        "total_call_oi": 9868,
        "total_put_oi": 10623,
        "max_call_oi_strike": 59.0,
        "max_put_oi_strike": 55.0,
        "avg_iv_calls": 0.3588,
        "avg_iv_puts": 0.3915,
        "iv_skew": 0.0327
      }
    ],
    "aggregate": {
      "total_pc_ratio_volume": 0.981,
      "total_pc_ratio_oi": 0.97,
      "total_call_volume": 64105,
      "total_put_volume": 62894,
      "total_call_oi": 569171,
      "total_put_oi": 552004
    },
    "sentiment": {
      "volume_signal": "bullish",
      "volume_note": "P/C(vol)=0.98 偏多",
      "oi_signal": "bullish",
      "skew_signal": "put_premium",
      "skew_note": "Put IV 显著高于 Call IV (skew=1.041) → 市场在积极买入下行保护",
      "key_put_support": 130.0,
      "key_call_resistance": 59.0
    }
  },
  "ovx_enhanced": {
    "latest": 72.34,
    "date": "2026-05-06",
    "avg_20d": 75.82,
    "avg_60d": 79.37,
    "percentile": 91.4,
    "vol_of_vol_5d": 2.8,
    "regime": "panic"
  },
  "updated": "2026-05-07T15:58:18Z"
}